sisx/__init__.py
sisx/cli.py
sisx/py.typed
sisx/templates/__init__.py
sisx/templates/app/connection.py
sisx/templates/app/environment.yml
sisx/templates/app/pyproject.toml
sisx/templates/app/requirements.txt
sisx/templates/app/snowflake.yml
sisx/templates/app/streamlit_app.py
sisx/templates/app/template.yml
sisx/templates/app/app_pages/cost_analysis.py
sisx/templates/app/app_pages/home.py
sisx/templates/app/app_pages/usage_metrics.py
sisx/utils/secrets.py
sisx/utils/snowcli.py
sisx/utils/templates.py
sisx/utils/toml_config.py
sisx/utils/yaml_config.py
sisx-0.1.9.dist-info/METADATA
sisx-0.1.9.dist-info/WHEEL
sisx-0.1.9.dist-info/entry_points.txt
sisx-0.1.9.dist-info/licenses/LICENSE.txt
sisx-0.1.9.dist-info/RECORD
