Metadata-Version: 2.4
Name: sisx
Version: 0.1.9
Summary: Python package to make it easy to develop, test and deploy performant streamlit-in-snowflake apps
Project-URL: Source, https://github.com/blackary/sisx
Project-URL: Tracker, https://github.com/blackary/sisx/issues
Author-email: Zachary Blackwood <zblackwo@gmail.com>
License: MIT
License-File: LICENSE.txt
Classifier: License :: OSI Approved :: MIT License
Classifier: Programming Language :: Python :: 3.10
Classifier: Programming Language :: Python :: 3.11
Classifier: Programming Language :: Python :: 3.12
Requires-Python: <3.13,>=3.10
Requires-Dist: numpy<2.0.0,>=1.24.4
Requires-Dist: pandas
Requires-Dist: plotly
Requires-Dist: pyarrow<19.0.0
Requires-Dist: pytest>=8.3.5
Requires-Dist: rich>=13.7.0
Requires-Dist: snowflake-cli>=3.7.0
Requires-Dist: snowflake-snowpark-python
Requires-Dist: streamlit
Requires-Dist: tomli>=2.0.1
Requires-Dist: typer
